{"pid":"28584","type":"component","log":"/disk/d11/tlq/567f2af0-0e1d-468f-b72d-8b9bc8150a58.log","metadata":{"files":{"/usr/lib/jvm/java-1.8.0-openjdk-1.8.0.252.b09-2.el7_8.x86_64/jre/lib/amd64/server/libjvm.so":{"path":"/usr/lib/jvm/java-1.8.0-openjdk-1.8.0.252.b09-2.el7_8.x86_64/jre/lib/amd64/server/libjvm.so","type":"file","pids":"28586","accesses":1},"/usr/lib/jvm/java-1.8.0-openjdk-1.8.0.252.b09-2.el7_8.x86_64/jre/lib/amd64/jvm.cfg":{"path":"/usr/lib/jvm/java-1.8.0-openjdk-1.8.0.252.b09-2.el7_8.x86_64/jre/lib/amd64/jvm.cfg","type":"file","pids":"28586","accesses":1}},"processes":{"28593":{"pid":28593,"ppid":"28587","files":"","type":"process","exited":"0"},"28595":{"pid":28595,"ppid":"28587","files":"","type":"process","exited":"0"},"28584":{"pid":"28584","ppid":"28584","files":"","type":"process"},"28594":{"pid":28594,"ppid":"28587","files":"","type":"process","exited":"0"},"28590":{"pid":28590,"ppid":"28587","files":"","type":"process","exited":"0"},"28589":{"pid":28589,"ppid":"28587","files":"","type":"process","exited":"0"},"28592":{"pid":28592,"ppid":"28587","files":"","type":"process","exited":"0"},"28591":{"pid":28591,"ppid":"28587","files":"","type":"process","exited":"0"},"28588":{"pid":28588,"ppid":"28587","files":"","type":"process","exited":"0"},"28586":{"pid":"28586","ppid":"28584","files":",\"/usr/lib/jvm/java-1.8.0-openjdk-1.8.0.252.b09-2.el7_8.x86_64/jre/lib/amd64/jvm.cfg\"","type":"process","exited":"0","envs":"\"_JAVA_LAUNCHER_DEBUG\",\"_JAVA_VERSION_SET\",\"JDK_ALTERNATE_VM\",\"LD_LIBRARY_PATH\",\"NMT_LEVEL_28586\",\"CLASSPATH\",\"_JAVA_SPLASH_JAR\",\"_JAVA_SPLASH_FILE\""},"28587":{"pid":28587,"ppid":"28586","files":"","type":"process","exited":"0"},"28564":{"pid":"28564","ppid":"28584","files":"","type":"process"}},"environment-variables":{"_JAVA_SPLASH_JAR":{"name":"_JAVA_SPLASH_JAR","values":"nil","type":"environment-variable","pids":"28586","accesses":1},"_JAVA_SPLASH_FILE":{"name":"_JAVA_SPLASH_FILE","values":"nil","type":"environment-variable","pids":"28586","accesses":1},"LD_LIBRARY_PATH":{"name":"LD_LIBRARY_PATH","values":"\"/afs/crc.nd.edu/group/ccl/software/x86_64/redhat7/ruby/current/lib:/afs/crc.nd.edu/group/ccl/software/x86_64/redhat7/graphviz/current/lib:/afs/crc.nd.edu/group/ccl/software/x86_64/redhat7/git/current/lib:/afs/crc.nd.edu/group/ccl/software/x86_64/redhat7/condor/current/lib:/afs/crc.nd.edu/group/ccl/software/x86_64/redhat7/clang/current/lib:/afs/crc.nd.edu/group/ccl/software/x86_64/redhat7/condor/current/lib:/afs/crc.nd.edu/group/ccl/software/x86_64/redhat7/cctools/current/lib:/opt/crc/usr/local/lib\"","type":"environment-variable","pids":"28586","accesses":1},"_JAVA_LAUNCHER_DEBUG":{"name":"_JAVA_LAUNCHER_DEBUG","values":"nil","type":"environment-variable","pids":"28586","accesses":1},"JDK_ALTERNATE_VM":{"name":"JDK_ALTERNATE_VM","values":"nil","type":"environment-variable","pids":"28586","accesses":1},"_JAVA_VERSION_SET":{"name":"_JAVA_VERSION_SET","values":"nil","type":"environment-variable","pids":"28586","accesses":1},"NMT_LEVEL_28586":{"name":"NMT_LEVEL_28586","values":"nil","type":"environment-variable","pids":"28586","accesses":1},"CLASSPATH":{"name":"CLASSPATH","values":"nil","type":"environment-variable","pids":"28586","accesses":1}}},"uuid":"567f2af0-0e1d-468f-b72d-8b9bc8150a58","command":"java -cp ./tools/maxent.jar density.MaxEnt -s outputs/Ibalia_montana_Cresson.csv -e data/layers/worldclim -o outputs/Ibalia_montana_Cresson nowarnings nocache autorun -z","host":"disc25.crc.nd.edu"}
