{"pid":"15295","type":"component","log":"/disk/d11/tlq/775b11c5-cbac-457b-b31b-0085a74a25d7.log","metadata":{"files":{"/usr/lib/jvm/java-1.8.0-openjdk-1.8.0.252.b09-2.el7_8.x86_64/jre/lib/amd64/server/libjvm.so":{"path":"/usr/lib/jvm/java-1.8.0-openjdk-1.8.0.252.b09-2.el7_8.x86_64/jre/lib/amd64/server/libjvm.so","type":"file","pids":"15297","accesses":1},"/usr/lib/jvm/java-1.8.0-openjdk-1.8.0.252.b09-2.el7_8.x86_64/jre/lib/amd64/jvm.cfg":{"path":"/usr/lib/jvm/java-1.8.0-openjdk-1.8.0.252.b09-2.el7_8.x86_64/jre/lib/amd64/jvm.cfg","type":"file","pids":"15297","accesses":1}},"processes":{"15305":{"pid":15305,"ppid":"15298","files":"","type":"process","exited":"1"},"15295":{"pid":"15295","ppid":"15295","files":"","type":"process"},"15301":{"pid":15301,"ppid":"15298","files":"","type":"process","exited":"1"},"15278":{"pid":"15278","ppid":"15295","files":"","type":"process"},"15302":{"pid":15302,"ppid":"15298","files":"","type":"process","exited":"1"},"15299":{"pid":15299,"ppid":"15298","files":"","type":"process","exited":"0"},"15306":{"pid":15306,"ppid":"15298","files":"","type":"process","exited":"0"},"15300":{"pid":15300,"ppid":"15298","files":"","type":"process","exited":"1"},"15303":{"pid":15303,"ppid":"15298","files":"","type":"process","exited":"1"},"15304":{"pid":15304,"ppid":"15298","files":"","type":"process","exited":"1"},"15298":{"pid":15298,"ppid":"15297","files":"","type":"process","exited":"0"},"15297":{"pid":"15297","ppid":"15295","files":",\"/usr/lib/jvm/java-1.8.0-openjdk-1.8.0.252.b09-2.el7_8.x86_64/jre/lib/amd64/jvm.cfg\"","type":"process","exited":"1","envs":"\"_JAVA_LAUNCHER_DEBUG\",\"_JAVA_VERSION_SET\",\"JDK_ALTERNATE_VM\",\"LD_LIBRARY_PATH\",\"NMT_LEVEL_15297\",\"CLASSPATH\",\"_JAVA_SPLASH_JAR\",\"_JAVA_SPLASH_FILE\""}},"environment-variables":{"_JAVA_SPLASH_JAR":{"name":"_JAVA_SPLASH_JAR","values":"nil","type":"environment-variable","pids":"15297","accesses":1},"_JAVA_SPLASH_FILE":{"name":"_JAVA_SPLASH_FILE","values":"nil","type":"environment-variable","pids":"15297","accesses":1},"LD_LIBRARY_PATH":{"name":"LD_LIBRARY_PATH","values":"\"/afs/crc.nd.edu/group/ccl/software/x86_64/redhat7/ruby/current/lib:/afs/crc.nd.edu/group/ccl/software/x86_64/redhat7/graphviz/current/lib:/afs/crc.nd.edu/group/ccl/software/x86_64/redhat7/git/current/lib:/afs/crc.nd.edu/group/ccl/software/x86_64/redhat7/condor/current/lib:/afs/crc.nd.edu/group/ccl/software/x86_64/redhat7/clang/current/lib:/afs/crc.nd.edu/group/ccl/software/x86_64/redhat7/condor/current/lib:/afs/crc.nd.edu/group/ccl/software/x86_64/redhat7/cctools/current/lib:/opt/crc/usr/local/lib\"","type":"environment-variable","pids":"15297","accesses":1},"_JAVA_LAUNCHER_DEBUG":{"name":"_JAVA_LAUNCHER_DEBUG","values":"nil","type":"environment-variable","pids":"15297","accesses":1},"JDK_ALTERNATE_VM":{"name":"JDK_ALTERNATE_VM","values":"nil","type":"environment-variable","pids":"15297","accesses":1},"_JAVA_VERSION_SET":{"name":"_JAVA_VERSION_SET","values":"nil","type":"environment-variable","pids":"15297","accesses":1},"NMT_LEVEL_15297":{"name":"NMT_LEVEL_15297","values":"nil","type":"environment-variable","pids":"15297","accesses":1},"CLASSPATH":{"name":"CLASSPATH","values":"nil","type":"environment-variable","pids":"15297","accesses":1}}},"uuid":"775b11c5-cbac-457b-b31b-0085a74a25d7","command":"java -cp ./tools/maxent.jar density.Project outputs/Dysstroma_concinnata_Stephens/Dysstroma_concinnata_Stephens.lambdas data/layers/worldclim outputs/Dysstroma_concinnata_Stephens_worldclim.asc nowarnings nocache autorun -z","host":"disc25.crc.nd.edu"}
