{"pid":"23327","type":"component","log":"/disk/d11/tlq/9eca5420-090f-4c1d-adaf-c255abf8ae1f.log","metadata":{"files":{"/usr/lib/jvm/java-1.8.0-openjdk-1.8.0.252.b09-2.el7_8.x86_64/jre/lib/amd64/server/libjvm.so":{"path":"/usr/lib/jvm/java-1.8.0-openjdk-1.8.0.252.b09-2.el7_8.x86_64/jre/lib/amd64/server/libjvm.so","type":"file","pids":"23329","accesses":1},"/usr/lib/jvm/java-1.8.0-openjdk-1.8.0.252.b09-2.el7_8.x86_64/jre/lib/amd64/jvm.cfg":{"path":"/usr/lib/jvm/java-1.8.0-openjdk-1.8.0.252.b09-2.el7_8.x86_64/jre/lib/amd64/jvm.cfg","type":"file","pids":"23329","accesses":1}},"processes":{"23330":{"pid":23330,"ppid":"23329","files":"","type":"process","exited":"0"},"23333":{"pid":23333,"ppid":"23330","files":"","type":"process","exited":"1"},"23339":{"pid":23339,"ppid":"23330","files":"","type":"process","exited":"0"},"23310":{"pid":"23310","ppid":"23327","files":"","type":"process"},"23336":{"pid":23336,"ppid":"23330","files":"","type":"process","exited":"1"},"23335":{"pid":23335,"ppid":"23330","files":"","type":"process","exited":"0"},"23327":{"pid":"23327","ppid":"23327","files":"","type":"process"},"23331":{"pid":23331,"ppid":"23330","files":"","type":"process","exited":"0"},"23338":{"pid":23338,"ppid":"23330","files":"","type":"process","exited":"1"},"23332":{"pid":23332,"ppid":"23330","files":"","type":"process","exited":"1"},"23329":{"pid":"23329","ppid":"23327","files":",\"/usr/lib/jvm/java-1.8.0-openjdk-1.8.0.252.b09-2.el7_8.x86_64/jre/lib/amd64/jvm.cfg\"","type":"process","exited":"1","envs":"\"_JAVA_LAUNCHER_DEBUG\",\"_JAVA_VERSION_SET\",\"JDK_ALTERNATE_VM\",\"LD_LIBRARY_PATH\",\"NMT_LEVEL_23329\",\"CLASSPATH\",\"_JAVA_SPLASH_JAR\",\"_JAVA_SPLASH_FILE\""},"23337":{"pid":23337,"ppid":"23330","files":"","type":"process","exited":"1"}},"environment-variables":{"_JAVA_SPLASH_JAR":{"name":"_JAVA_SPLASH_JAR","values":"nil","type":"environment-variable","pids":"23329","accesses":1},"_JAVA_SPLASH_FILE":{"name":"_JAVA_SPLASH_FILE","values":"nil","type":"environment-variable","pids":"23329","accesses":1},"LD_LIBRARY_PATH":{"name":"LD_LIBRARY_PATH","values":"\"/afs/crc.nd.edu/group/ccl/software/x86_64/redhat7/ruby/current/lib:/afs/crc.nd.edu/group/ccl/software/x86_64/redhat7/graphviz/current/lib:/afs/crc.nd.edu/group/ccl/software/x86_64/redhat7/git/current/lib:/afs/crc.nd.edu/group/ccl/software/x86_64/redhat7/condor/current/lib:/afs/crc.nd.edu/group/ccl/software/x86_64/redhat7/clang/current/lib:/afs/crc.nd.edu/group/ccl/software/x86_64/redhat7/condor/current/lib:/afs/crc.nd.edu/group/ccl/software/x86_64/redhat7/cctools/current/lib:/opt/crc/usr/local/lib\"","type":"environment-variable","pids":"23329","accesses":1},"_JAVA_LAUNCHER_DEBUG":{"name":"_JAVA_LAUNCHER_DEBUG","values":"nil","type":"environment-variable","pids":"23329","accesses":1},"JDK_ALTERNATE_VM":{"name":"JDK_ALTERNATE_VM","values":"nil","type":"environment-variable","pids":"23329","accesses":1},"_JAVA_VERSION_SET":{"name":"_JAVA_VERSION_SET","values":"nil","type":"environment-variable","pids":"23329","accesses":1},"NMT_LEVEL_23329":{"name":"NMT_LEVEL_23329","values":"nil","type":"environment-variable","pids":"23329","accesses":1},"CLASSPATH":{"name":"CLASSPATH","values":"nil","type":"environment-variable","pids":"23329","accesses":1}}},"uuid":"9eca5420-090f-4c1d-adaf-c255abf8ae1f","command":"java -cp ./tools/maxent.jar density.Project outputs/Pityophthorus_carinulatus_Swaine/Pityophthorus_carinulatus_Swaine.lambdas data/layers/worldclim outputs/Pityophthorus_carinulatus_Swaine_worldclim.asc nowarnings nocache autorun -z","host":"disc25.crc.nd.edu"}
